visualequation/__init__.py
visualequation/__main__.py
visualequation/commons.py
visualequation/conversions.py
visualequation/eq.py
visualequation/eqhist.py
visualequation/eqlabel.py
visualequation/eqsel.py
visualequation/eqtools.py
visualequation/errors.py
visualequation/game.py
visualequation/latexdialogs.py
visualequation/symbolstab.py
visualequation/symbols/__init__.py
visualequation/symbols/accents.py
visualequation/symbols/arrows.py
visualequation/symbols/constructs.py
visualequation/symbols/delimiters.py
visualequation/symbols/functions.py
visualequation/symbols/lists.py
visualequation/symbols/manylines.py
visualequation/symbols/operators.py
visualequation/symbols/relations.py
visualequation/symbols/symbols.py
visualequation/symbols/text.py
visualequation/symbols/utils.py
visualequation/symbols/variablesize.py
visualequation-0.3.9.data/data/share/applications/visualequation.desktop
visualequation-0.3.9.data/data/share/locale/es/LC_MESSAGES/visualequation.mo
visualequation-0.3.9.data/data/share/visualequation/eq_template.tex
visualequation-0.3.9.data/data/share/visualequation/visualequation.png
visualequation-0.3.9.dist-info/DESCRIPTION.rst
visualequation-0.3.9.dist-info/METADATA
visualequation-0.3.9.dist-info/RECORD
visualequation-0.3.9.dist-info/WHEEL
visualequation-0.3.9.dist-info/entry_points.txt
visualequation-0.3.9.dist-info/metadata.json
visualequation-0.3.9.dist-info/top_level.txt
