Metadata-Version: 2.0
Name: visualequation
Version: 0.3.9
Summary: An equation editor powered by LaTeX
Home-page: https://github.com/daniel-molina/visualequation
Author: Daniel Molina Garcia
Author-email: lluvia@autistici.org
License: UNKNOWN
Keywords: mathematics equation editor latex wysiwyg formulas
Platform: UNKNOWN
Classifier: Programming Language :: Python :: 3
Classifier: License :: OSI Approved :: GNU General Public License v3 or later (GPLv3+)
Classifier: Operating System :: POSIX :: Linux
Classifier: Environment :: X11 Applications :: Qt
Classifier: Topic :: Scientific/Engineering :: Mathematics
Classifier: Intended Audience :: Science/Research
Classifier: Intended Audience :: Education
